drugstools/BCfunc.py
drugstools/__init__.py
drugstools/checktime.py
drugstools/countUMI.py
drugstools/install_check.py
drugstools/main.py
drugstools/pipeline_params.py
drugstools/transformer.py
drugstools-1.0.0.dist-info/LICENSE.md
drugstools-1.0.0.dist-info/METADATA
drugstools-1.0.0.dist-info/WHEEL
drugstools-1.0.0.dist-info/entry_points.txt
drugstools-1.0.0.dist-info/top_level.txt
drugstools-1.0.0.dist-info/RECORD
